odoo9_addon_base_name_search_improved-9.0.1.0.0.99.dev12-py2.7-nspkg.pth
odoo9_addon_base_name_search_improved-9.0.1.0.0.99.dev12.dist-info/DESCRIPTION.rst
odoo9_addon_base_name_search_improved-9.0.1.0.0.99.dev12.dist-info/METADATA
odoo9_addon_base_name_search_improved-9.0.1.0.0.99.dev12.dist-info/RECORD
odoo9_addon_base_name_search_improved-9.0.1.0.0.99.dev12.dist-info/WHEEL
odoo9_addon_base_name_search_improved-9.0.1.0.0.99.dev12.dist-info/metadata.json
odoo9_addon_base_name_search_improved-9.0.1.0.0.99.dev12.dist-info/namespace_packages.txt
odoo9_addon_base_name_search_improved-9.0.1.0.0.99.dev12.dist-info/top_level.txt
odoo_addons/base_name_search_improved/README.rst
odoo_addons/base_name_search_improved/__init__.py
odoo_addons/base_name_search_improved/__openerp__.py
odoo_addons/base_name_search_improved/i18n/base_name_search_improved.pot
odoo_addons/base_name_search_improved/i18n/ca.po
odoo_addons/base_name_search_improved/i18n/de.po
odoo_addons/base_name_search_improved/i18n/es.po
odoo_addons/base_name_search_improved/i18n/es_ES.po
odoo_addons/base_name_search_improved/i18n/eu.po
odoo_addons/base_name_search_improved/i18n/fi.po
odoo_addons/base_name_search_improved/i18n/fr.po
odoo_addons/base_name_search_improved/i18n/hr.po
odoo_addons/base_name_search_improved/i18n/hr_HR.po
odoo_addons/base_name_search_improved/i18n/it.po
odoo_addons/base_name_search_improved/i18n/nb_NO.po
odoo_addons/base_name_search_improved/i18n/nl.po
odoo_addons/base_name_search_improved/i18n/pt_BR.po
odoo_addons/base_name_search_improved/i18n/sl.po
odoo_addons/base_name_search_improved/i18n/tr.po
odoo_addons/base_name_search_improved/i18n/tr_TR.po
odoo_addons/base_name_search_improved/i18n/zh_CN.po
odoo_addons/base_name_search_improved/images/image0.png
odoo_addons/base_name_search_improved/images/image1.png
odoo_addons/base_name_search_improved/images/image2.png
odoo_addons/base_name_search_improved/models/__init__.py
odoo_addons/base_name_search_improved/models/ir_model.py
odoo_addons/base_name_search_improved/static/description/icon.png
odoo_addons/base_name_search_improved/tests/__init__.py
odoo_addons/base_name_search_improved/tests/test_name_search.py
odoo_addons/base_name_search_improved/views/ir_model.xml
