Metadata-Version: 2.0
Name: odoo9-addon-base-name-search-improved
Version: 9.0.1.0.0.99.dev12
Summary: Friendlier search when typing in relation fields
Home-page: https://odoo-community.org/
Author: Daniel Reis, Odoo Community Association (OCA)
Author-email: support@odoo-community.org
License: AGPL-3
Platform: UNKNOWN
Classifier: Programming Language :: Python
Classifier: Framework :: Odoo
Classifier: License :: OSI Approved :: GNU Affero General Public License v3
Requires-Python: ~=2.7
Requires-Dist: odoo (<9.1a,>=9.0a)
